Workbook

Sheet july_cfd_trd
F1: Current | K1: Revised
B2: Ticker | C2: Name | D2: Class | E2: Category | F2: CO | G2: MC | H2: MO | I2: MA | J2: AG | K2: CO | L2: MC | M2: MO | N2: MA | O2: AG | P2: ST (3Mo) | Q2: SMT (6Mo) | R2: MT (12Mo) | S2: LT (18Mo) | T2: LT2 (2.5-3.0Y) | U2: 46112
A3: Fund Change | B3: ANAIX | C3: =_xlfn.XLOOKUP(B3,'[1]_Funds 2026 04 01'!$B:$B,'[1]_Funds 2026 04 01'!$A:$A) -> AB Global Bond I | D3: =_xlfn.XLOOKUP(E3,[2]Sheet1!$D:$D,[2]Sheet1!$B:$B) -> Fixed Income | E3: =_xlfn.XLOOKUP(B3,'[1]_Funds 2026 04 01'!$B:$B,'[1]_Funds 2026 04 01'!$D:$D) -> Global Fixed Income | F3: =IFERROR(IF(_xlfn.XLOOKUP(B3,july_cfd_trd_1co!C:C,july_cfd_trd_1co!G:G)=0,"-",_xlfn.XLOOKUP(B3,july_cfd_trd_1co!C:C,july_cfd_trd_1co!G:G)),"-") -> 0.06 | G3: - | H3: =IFERROR(IF(_xlfn.XLOOKUP(B3,july_cfd_trd_3mo!C:C,july_cfd_trd_3mo!G:G)=0,"-",_xlfn.XLOOKUP(B3,july_cfd_trd_3mo!C:C,july_cfd_trd_3mo!G:G)),"-") -> 0.05 | I3: =IFERROR(IF(_xlfn.XLOOKUP(B3,july_cfd_trd_4ma!C:C,july_cfd_trd_4ma!G:G)=0,"-",_xlfn.XLOOKUP(B3,july_cfd_trd_4ma!C:C,july_cfd_trd_4ma!G:G)),"-") -> 0.05 | J3: =IFERROR(IF(_xlfn.XLOOKUP(B3,july_cfd_trd_5ag!C:C,july_cfd_trd_5ag!G:G)=0,"-",_xlfn.XLOOKUP(B3,july_cfd_trd_5ag!C:C,july_cfd_trd_5ag!G:G)),"-") -> - | K3: - | L3: - | M3: - | N3: - | O3: - | P3: =_xlfn.XLOOKUP($B3,'[3]All Funds'!$B:$B,'[3]All Funds'!T:T) -> 0.47060087 | Q3: =_xlfn.XLOOKUP($B3,'[3]All Funds'!$B:$B,'[3]All Funds'!U:U) -> 0.45187743 | R3: =_xlfn.XLOOKUP($B3,'[3]All Funds'!$B:$B,'[3]All Funds'!V:V) -> 0.4543489 | S3: =_xlfn.XLOOKUP($B3,'[3]All Funds'!$B:$B,'[3]All Funds'!W:W) -> 0.42778249 | T3: =_xlfn.XLOOKUP($B3,'[3]All Funds'!$B:$B,'[3]All Funds'!X:X) -> 0.38780413 | U3: =_xlfn.XLOOKUP($B3,'[3]All Funds'!$B:$B,'[3]All Funds'!Y:Y) -> 0.47902228
A4: Category Elimination | B4: AGDIX | C4: =_xlfn.XLOOKUP(B4,'[1]_Funds 2026 04 01'!$B:$B,'[1]_Funds 2026 04 01'!$A:$A) -> AB High Income I | D4: =_xlfn.XLOOKUP(E4,[2]Sheet1!$D:$D,[2]Sheet1!$B:$B) -> Fixed Income | E4: =_xlfn.XLOOKUP(B4,'[1]_Funds 2026 04 01'!$B:$B,'[1]_Funds 2026 04 01'!$D:$D) -> High Yield | F4: =IFERROR(IF(_xlfn.XLOOKUP(B4,july_cfd_trd_1co!C:C,july_cfd_trd_1co!G:G)=0,"-",_xlfn.XLOOKUP(B4,july_cfd_trd_1co!C:C,july_cfd_trd_1co!G:G)),"-") -> 0.05 | G4: - | H4: =IFERROR(IF(_xlfn.XLOOKUP(B4,july_cfd_trd_3mo!C:C,july_cfd_trd_3mo!G:G)=0,"-",_xlfn.XLOOKUP(B4,july_cfd_trd_3mo!C:C,july_cfd_trd_3mo!G:G)),"-") -> 0.05 | I4: =IFERROR(IF(_xlfn.XLOOKUP(B4,july_cfd_trd_4ma!C:C,july_cfd_trd_4ma!G:G)=0,"-",_xlfn.XLOOKUP(B4,july_cfd_trd_4ma!C:C,july_cfd_trd_4ma!G:G)),"-") -> - | J4: =IFERROR(IF(_xlfn.XLOOKUP(B4,july_cfd_trd_5ag!C:C,july_cfd_trd_5ag!G:G)=0,"-",_xlfn.XLOOKUP(B4,july_cfd_trd_5ag!C:C,july_cfd_trd_5ag!G:G)),"-") -> - | K4: - | L4: - | M4: - | N4: - | O4: - | P4: =_xlfn.XLOOKUP($B4,'[3]All Funds'!$B:$B,'[3]All Funds'!T:T) -> 0.2208446 | Q4: =_xlfn.XLOOKUP($B4,'[3]All Funds'!$B:$B,'[3]All Funds'!U:U) -> 0.17356737 | R4: =_xlfn.XLOOKUP($B4,'[3]All Funds'!$B:$B,'[3]All Funds'!V:V) -> 0.1705645 | S4: =_xlfn.XLOOKUP($B4,'[3]All Funds'!$B:$B,'[3]All Funds'!W:W) -> 0.18942735 | T4: =_xlfn.XLOOKUP($B4,'[3]All Funds'!$B:$B,'[3]All Funds'!X:X) -> 0.22700172 | U4: =_xlfn.XLOOKUP($B4,'[3]All Funds'!$B:$B,'[3]All Funds'!Y:Y) -> 0.28532755
B5: DODIX | C5: =_xlfn.XLOOKUP(B5,'[1]_Funds 2026 04 01'!$B:$B,'[1]_Funds 2026 04 01'!$A:$A) -> Dodge & Cox Income I | D5: =_xlfn.XLOOKUP(E5,[2]Sheet1!$D:$D,[2]Sheet1!$B:$B) -> Fixed Income | E5: =_xlfn.XLOOKUP(B5,'[1]_Funds 2026 04 01'!$B:$B,'[1]_Funds 2026 04 01'!$D:$D) -> Intermediate Term Bond (Core Plus) | F5: =IFERROR(IF(_xlfn.XLOOKUP(B5,july_cfd_trd_1co!C:C,july_cfd_trd_1co!G:G)=0,"-",_xlfn.XLOOKUP(B5,july_cfd_trd_1co!C:C,july_cfd_trd_1co!G:G)),"-") -> 0.15 | G5: - | H5: =IFERROR(IF(_xlfn.XLOOKUP(B5,july_cfd_trd_3mo!C:C,july_cfd_trd_3mo!G:G)=0,"-",_xlfn.XLOOKUP(B5,july_cfd_trd_3mo!C:C,july_cfd_trd_3mo!G:G)),"-") -> 0.1 | I5: =IFERROR(IF(_xlfn.XLOOKUP(B5,july_cfd_trd_4ma!C:C,july_cfd_trd_4ma!G:G)=0,"-",_xlfn.XLOOKUP(B5,july_cfd_trd_4ma!C:C,july_cfd_trd_4ma!G:G)),"-") -> 0.05 | J5: =IFERROR(IF(_xlfn.XLOOKUP(B5,july_cfd_trd_5ag!C:C,july_cfd_trd_5ag!G:G)=0,"-",_xlfn.XLOOKUP(B5,july_cfd_trd_5ag!C:C,july_cfd_trd_5ag!G:G)),"-") -> - | K5: - | L5: - | M5: - | N5: - | O5: - | P5: =_xlfn.XLOOKUP($B5,'[3]All Funds'!$B:$B,'[3]All Funds'!T:T) -> 0.039074308 | Q5: =_xlfn.XLOOKUP($B5,'[3]All Funds'!$B:$B,'[3]All Funds'!U:U) -> 0.057255495 | R5: =_xlfn.XLOOKUP($B5,'[3]All Funds'!$B:$B,'[3]All Funds'!V:V) -> 0.083259584 | S5: =_xlfn.XLOOKUP($B5,'[3]All Funds'!$B:$B,'[3]All Funds'!W:W) -> 0.064736095 | T5: =_xlfn.XLOOKUP($B5,'[3]All Funds'!$B:$B,'[3]All Funds'!X:X) -> 0.041189077 | U5: =_xlfn.XLOOKUP($B5,'[3]All Funds'!$B:$B,'[3]All Funds'!Y:Y) -> 0.036096491
B6: BFFAX | C6: =_xlfn.XLOOKUP(B6,'[1]_Funds 2026 04 01'!$B:$B,'[1]_Funds 2026 04 01'!$A:$A) -> American Funds Bond Fund of Amer F3 | D6: =_xlfn.XLOOKUP(E6,[2]Sheet1!$D:$D,[2]Sheet1!$B:$B) -> Fixed Income | E6: =_xlfn.XLOOKUP(B6,'[1]_Funds 2026 04 01'!$B:$B,'[1]_Funds 2026 04 01'!$D:$D) -> Intermediate Term Bond (Core) | F6: =IFERROR(IF(_xlfn.XLOOKUP(B6,july_cfd_trd_1co!C:C,july_cfd_trd_1co!G:G)=0,"-",_xlfn.XLOOKUP(B6,july_cfd_trd_1co!C:C,july_cfd_trd_1co!G:G)),"-") -> 0.1 | G6: - | H6: =IFERROR(IF(_xlfn.XLOOKUP(B6,july_cfd_trd_3mo!C:C,july_cfd_trd_3mo!G:G)=0,"-",_xlfn.XLOOKUP(B6,july_cfd_trd_3mo!C:C,july_cfd_trd_3mo!G:G)),"-") -> 0.08 | I6: =IFERROR(IF(_xlfn.XLOOKUP(B6,july_cfd_trd_4ma!C:C,july_cfd_trd_4ma!G:G)=0,"-",_xlfn.XLOOKUP(B6,july_cfd_trd_4ma!C:C,july_cfd_trd_4ma!G:G)),"-") -> 0.05 | J6: =IFERROR(IF(_xlfn.XLOOKUP(B6,july_cfd_trd_5ag!C:C,july_cfd_trd_5ag!G:G)=0,"-",_xlfn.XLOOKUP(B6,july_cfd_trd_5ag!C:C,july_cfd_trd_5ag!G:G)),"-") -> - | K6: - | L6: - | M6: - | N6: - | O6: - | P6: =_xlfn.XLOOKUP($B6,'[3]All Funds'!$B:$B,'[3]All Funds'!T:T) -> 0.14783265 | Q6: =_xlfn.XLOOKUP($B6,'[3]All Funds'!$B:$B,'[3]All Funds'!U:U) -> 0.13026554 | R6: =_xlfn.XLOOKUP($B6,'[3]All Funds'!$B:$B,'[3]All Funds'!V:V) -> 0.13267339 | S6: =_xlfn.XLOOKUP($B6,'[3]All Funds'!$B:$B,'[3]All Funds'!W:W) -> 0.13682935 | T6: =_xlfn.XLOOKUP($B6,'[3]All Funds'!$B:$B,'[3]All Funds'!X:X) -> 0.15459684 | U6: =_xlfn.XLOOKUP($B6,'[3]All Funds'!$B:$B,'[3]All Funds'!Y:Y) -> 0.21322281
B7: RGVGX | C7: =_xlfn.XLOOKUP(B7,'[1]_Funds 2026 04 01'!$B:$B,'[1]_Funds 2026 04 01'!$A:$A) -> American Funds US Government Sec R6 | D7: =_xlfn.XLOOKUP(E7,[2]Sheet1!$D:$D,[2]Sheet1!$B:$B) -> Fixed Income | E7: =_xlfn.XLOOKUP(B7,'[1]_Funds 2026 04 01'!$B:$B,'[1]_Funds 2026 04 01'!$D:$D) -> Intermediate Term Government | F7: =IFERROR(IF(_xlfn.XLOOKUP(B7,july_cfd_trd_1co!C:C,july_cfd_trd_1co!G:G)=0,"-",_xlfn.XLOOKUP(B7,july_cfd_trd_1co!C:C,july_cfd_trd_1co!G:G)),"-") -> 0.15 | G7: - | H7: =IFERROR(IF(_xlfn.XLOOKUP(B7,july_cfd_trd_3mo!C:C,july_cfd_trd_3mo!G:G)=0,"-",_xlfn.XLOOKUP(B7,july_cfd_trd_3mo!C:C,july_cfd_trd_3mo!G:G)),"-") -> 0.05 | I7: =IFERROR(IF(_xlfn.XLOOKUP(B7,july_cfd_trd_4ma!C:C,july_cfd_trd_4ma!G:G)=0,"-",_xlfn.XLOOKUP(B7,july_cfd_trd_4ma!C:C,july_cfd_trd_4ma!G:G)),"-") -> - | J7: =IFERROR(IF(_xlfn.XLOOKUP(B7,july_cfd_trd_5ag!C:C,july_cfd_trd_5ag!G:G)=0,"-",_xlfn.XLOOKUP(B7,july_cfd_trd_5ag!C:C,july_cfd_trd_5ag!G:G)),"-") -> - | K7: - | L7: - | M7: - | N7: - | O7: - | P7: =_xlfn.XLOOKUP($B7,'[3]All Funds'!$B:$B,'[3]All Funds'!T:T) -> 0.033837554 | Q7: =_xlfn.XLOOKUP($B7,'[3]All Funds'!$B:$B,'[3]All Funds'!U:U) -> 0.030426149 | R7: =_xlfn.XLOOKUP($B7,'[3]All Funds'!$B:$B,'[3]All Funds'!V:V) -> 0.028381043 | S7: =_xlfn.XLOOKUP($B7,'[3]All Funds'!$B:$B,'[3]All Funds'!W:W) -> 0.035999199 | T7: =_xlfn.XLOOKUP($B7,'[3]All Funds'!$B:$B,'[3]All Funds'!X:X) -> 0.074252673 | U7: =_xlfn.XLOOKUP($B7,'[3]All Funds'!$B:$B,'[3]All Funds'!Y:Y) -> 0.033727678
B8: RMDUX | C8: =_xlfn.XLOOKUP(B8,'[1]_Funds 2026 04 01'!$B:$B,'[1]_Funds 2026 04 01'!$A:$A) -> American Funds Multi-Sector Income R-6 | D8: =_xlfn.XLOOKUP(E8,[2]Sheet1!$D:$D,[2]Sheet1!$B:$B) -> Fixed Income | E8: =_xlfn.XLOOKUP(B8,'[1]_Funds 2026 04 01'!$B:$B,'[1]_Funds 2026 04 01'!$D:$D) -> Multisector Bond | F8: =IFERROR(IF(_xlfn.XLOOKUP(B8,july_cfd_trd_1co!C:C,july_cfd_trd_1co!G:G)=0,"-",_xlfn.XLOOKUP(B8,july_cfd_trd_1co!C:C,july_cfd_trd_1co!G:G)),"-") -> 0.11 | G8: - | H8: =IFERROR(IF(_xlfn.XLOOKUP(B8,july_cfd_trd_3mo!C:C,july_cfd_trd_3mo!G:G)=0,"-",_xlfn.XLOOKUP(B8,july_cfd_trd_3mo!C:C,july_cfd_trd_3mo!G:G)),"-") -> 0.07 | I8: =IFERROR(IF(_xlfn.XLOOKUP(B8,july_cfd_trd_4ma!C:C,july_cfd_trd_4ma!G:G)=0,"-",_xlfn.XLOOKUP(B8,july_cfd_trd_4ma!C:C,july_cfd_trd_4ma!G:G)),"-") -> 0.05 | J8: =IFERROR(IF(_xlfn.XLOOKUP(B8,july_cfd_trd_5ag!C:C,july_cfd_trd_5ag!G:G)=0,"-",_xlfn.XLOOKUP(B8,july_cfd_trd_5ag!C:C,july_cfd_trd_5ag!G:G)),"-") -> - | K8: - | L8: - | M8: - | N8: - | O8: - | P8: =_xlfn.XLOOKUP($B8,'[3]All Funds'!$B:$B,'[3]All Funds'!T:T) -> 0.16080458 | Q8: =_xlfn.XLOOKUP($B8,'[3]All Funds'!$B:$B,'[3]All Funds'!U:U) -> 0.16159251 | R8: =_xlfn.XLOOKUP($B8,'[3]All Funds'!$B:$B,'[3]All Funds'!V:V) -> 0.13883237 | S8: =_xlfn.XLOOKUP($B8,'[3]All Funds'!$B:$B,'[3]All Funds'!W:W) -> 0.096194576 | T8: =_xlfn.XLOOKUP($B8,'[3]All Funds'!$B:$B,'[3]All Funds'!X:X) -> 0.087764178 | U8: =_xlfn.XLOOKUP($B8,'[3]All Funds'!$B:$B,'[3]All Funds'!Y:Y) -> 0.082317057
A9: Fund Change | B9: FSHBX | C9: =_xlfn.XLOOKUP(B9,'[1]_Funds 2026 04 01'!$B:$B,'[1]_Funds 2026 04 01'!$A:$A) -> Fidelity Short-Term Bond | D9: =_xlfn.XLOOKUP(E9,[2]Sheet1!$D:$D,[2]Sheet1!$B:$B) -> Fixed Income | E9: =_xlfn.XLOOKUP(B9,'[1]_Funds 2026 04 01'!$B:$B,'[1]_Funds 2026 04 01'!$D:$D) -> Short Term Bond | F9: =IFERROR(IF(_xlfn.XLOOKUP(B9,july_cfd_trd_1co!C:C,july_cfd_trd_1co!G:G)=0,"-",_xlfn.XLOOKUP(B9,july_cfd_trd_1co!C:C,july_cfd_trd_1co!G:G)),"-") -> 0.1 | G9: - | H9: =IFERROR(IF(_xlfn.XLOOKUP(B9,july_cfd_trd_3mo!C:C,july_cfd_trd_3mo!G:G)=0,"-",_xlfn.XLOOKUP(B9,july_cfd_trd_3mo!C:C,july_cfd_trd_3mo!G:G)),"-") -> - | I9: =IFERROR(IF(_xlfn.XLOOKUP(B9,july_cfd_trd_4ma!C:C,july_cfd_trd_4ma!G:G)=0,"-",_xlfn.XLOOKUP(B9,july_cfd_trd_4ma!C:C,july_cfd_trd_4ma!G:G)),"-") -> - | J9: =IFERROR(IF(_xlfn.XLOOKUP(B9,july_cfd_trd_5ag!C:C,july_cfd_trd_5ag!G:G)=0,"-",_xlfn.XLOOKUP(B9,july_cfd_trd_5ag!C:C,july_cfd_trd_5ag!G:G)),"-") -> - | K9: - | L9: - | M9: - | N9: - | O9: - | P9: =_xlfn.XLOOKUP($B9,'[3]All Funds'!$B:$B,'[3]All Funds'!T:T) -> 0.41247509 | Q9: =_xlfn.XLOOKUP($B9,'[3]All Funds'!$B:$B,'[3]All Funds'!U:U) -> 0.44717721 | R9: =_xlfn.XLOOKUP($B9,'[3]All Funds'!$B:$B,'[3]All Funds'!V:V) -> 0.43534438 | S9: =_xlfn.XLOOKUP($B9,'[3]All Funds'!$B:$B,'[3]All Funds'!W:W) -> 0.41192823 | T9: =_xlfn.XLOOKUP($B9,'[3]All Funds'!$B:$B,'[3]All Funds'!X:X) -> 0.37183709 | U9: =_xlfn.XLOOKUP($B9,'[3]All Funds'!$B:$B,'[3]All Funds'!Y:Y) -> 0.35468272
A10: Fund Change | B10: GQGIX | C10: =_xlfn.XLOOKUP(B10,'[1]_Funds 2026 04 01'!$B:$B,'[1]_Funds 2026 04 01'!$A:$A) -> GQG Partners Emerging Markets EquityInst | D10: =_xlfn.XLOOKUP(E10,[2]Sheet1!$D:$D,[2]Sheet1!$B:$B) -> Equity | E10: =_xlfn.XLOOKUP(B10,'[1]_Funds 2026 04 01'!$B:$B,'[1]_Funds 2026 04 01'!$D:$D) -> Emerging Markets Equity | F10: =IFERROR(IF(_xlfn.XLOOKUP(B10,july_cfd_trd_1co!C:C,july_cfd_trd_1co!G:G)=0,"-",_xlfn.XLOOKUP(B10,july_cfd_trd_1co!C:C,july_cfd_trd_1co!G:G)),"-") -> - | G10: - | H10: =IFERROR(IF(_xlfn.XLOOKUP(B10,july_cfd_trd_3mo!C:C,july_cfd_trd_3mo!G:G)=0,"-",_xlfn.XLOOKUP(B10,july_cfd_trd_3mo!C:C,july_cfd_trd_3mo!G:G)),"-") -> 0.05 | I10: =IFERROR(IF(_xlfn.XLOOKUP(B10,july_cfd_trd_4ma!C:C,july_cfd_trd_4ma!G:G)=0,"-",_xlfn.XLOOKUP(B10,july_cfd_trd_4ma!C:C,july_cfd_trd_4ma!G:G)),"-") -> 0.08 | J10: =IFERROR(IF(_xlfn.XLOOKUP(B10,july_cfd_trd_5ag!C:C,july_cfd_trd_5ag!G:G)=0,"-",_xlfn.XLOOKUP(B10,july_cfd_trd_5ag!C:C,july_cfd_trd_5ag!G:G)),"-") -> 0.11 | K10: - | L10: - | M10: - | N10: - | O10: - | P10: =_xlfn.XLOOKUP($B10,'[3]All Funds'!$B:$B,'[3]All Funds'!T:T) -> 0.65670709 | Q10: =_xlfn.XLOOKUP($B10,'[3]All Funds'!$B:$B,'[3]All Funds'!U:U) -> 0.67921044 | R10: =_xlfn.XLOOKUP($B10,'[3]All Funds'!$B:$B,'[3]All Funds'!V:V) -> 0.59089305 | S10: =_xlfn.XLOOKUP($B10,'[3]All Funds'!$B:$B,'[3]All Funds'!W:W) -> 0.38756379 | T10: =_xlfn.XLOOKUP($B10,'[3]All Funds'!$B:$B,'[3]All Funds'!X:X) -> 0.22326369 | U10: =_xlfn.XLOOKUP($B10,'[3]All Funds'!$B:$B,'[3]All Funds'!Y:Y) -> 0.61966906
B11: RERGX | C11: =_xlfn.XLOOKUP(B11,'[1]_Funds 2026 04 01'!$B:$B,'[1]_Funds 2026 04 01'!$A:$A) -> American Funds EUPAC R6 | D11: =_xlfn.XLOOKUP(E11,[2]Sheet1!$D:$D,[2]Sheet1!$B:$B) -> Equity | E11: =_xlfn.XLOOKUP(B11,'[1]_Funds 2026 04 01'!$B:$B,'[1]_Funds 2026 04 01'!$D:$D) -> International Large Cap Growth | F11: =IFERROR(IF(_xlfn.XLOOKUP(B11,july_cfd_trd_1co!C:C,july_cfd_trd_1co!G:G)=0,"-",_xlfn.XLOOKUP(B11,july_cfd_trd_1co!C:C,july_cfd_trd_1co!G:G)),"-") -> 0.05 | G11: - | H11: =IFERROR(IF(_xlfn.XLOOKUP(B11,july_cfd_trd_3mo!C:C,july_cfd_trd_3mo!G:G)=0,"-",_xlfn.XLOOKUP(B11,july_cfd_trd_3mo!C:C,july_cfd_trd_3mo!G:G)),"-") -> 0.13 | I11: =IFERROR(IF(_xlfn.XLOOKUP(B11,july_cfd_trd_4ma!C:C,july_cfd_trd_4ma!G:G)=0,"-",_xlfn.XLOOKUP(B11,july_cfd_trd_4ma!C:C,july_cfd_trd_4ma!G:G)),"-") -> 0.17 | J11: =IFERROR(IF(_xlfn.XLOOKUP(B11,july_cfd_trd_5ag!C:C,july_cfd_trd_5ag!G:G)=0,"-",_xlfn.XLOOKUP(B11,july_cfd_trd_5ag!C:C,july_cfd_trd_5ag!G:G)),"-") -> 0.21 | K11: - | L11: - | M11: - | N11: - | O11: - | P11: =_xlfn.XLOOKUP($B11,'[3]All Funds'!$B:$B,'[3]All Funds'!T:T) -> 0.068597199 | Q11: =_xlfn.XLOOKUP($B11,'[3]All Funds'!$B:$B,'[3]All Funds'!U:U) -> 0.082115171 | R11: =_xlfn.XLOOKUP($B11,'[3]All Funds'!$B:$B,'[3]All Funds'!V:V) -> 0.091896508 | S11: =_xlfn.XLOOKUP($B11,'[3]All Funds'!$B:$B,'[3]All Funds'!W:W) -> 0.091896508 | T11: =_xlfn.XLOOKUP($B11,'[3]All Funds'!$B:$B,'[3]All Funds'!X:X) -> 0.091896508 | U11: =_xlfn.XLOOKUP($B11,'[3]All Funds'!$B:$B,'[3]All Funds'!Y:Y) -> 0.058450786
B12: SPHQ | C12: =_xlfn.XLOOKUP(B12,'[1]_Funds 2026 04 01'!$B:$B,'[1]_Funds 2026 04 01'!$A:$A) -> Invesco S&P 500® Quality ETF | D12: =_xlfn.XLOOKUP(E12,[2]Sheet1!$D:$D,[2]Sheet1!$B:$B) -> Equity | E12: =_xlfn.XLOOKUP(B12,'[1]_Funds 2026 04 01'!$B:$B,'[1]_Funds 2026 04 01'!$D:$D) -> Large Cap Blend | F12: =IFERROR(IF(_xlfn.XLOOKUP(B12,july_cfd_trd_1co!C:C,july_cfd_trd_1co!G:G)=0,"-",_xlfn.XLOOKUP(B12,july_cfd_trd_1co!C:C,july_cfd_trd_1co!G:G)),"-") -> - | G12: - | H12: =IFERROR(IF(_xlfn.XLOOKUP(B12,july_cfd_trd_3mo!C:C,july_cfd_trd_3mo!G:G)=0,"-",_xlfn.XLOOKUP(B12,july_cfd_trd_3mo!C:C,july_cfd_trd_3mo!G:G)),"-") -> 0.06 | I12: =IFERROR(IF(_xlfn.XLOOKUP(B12,july_cfd_trd_4ma!C:C,july_cfd_trd_4ma!G:G)=0,"-",_xlfn.XLOOKUP(B12,july_cfd_trd_4ma!C:C,july_cfd_trd_4ma!G:G)),"-") -> 0.11 | J12: =IFERROR(IF(_xlfn.XLOOKUP(B12,july_cfd_trd_5ag!C:C,july_cfd_trd_5ag!G:G)=0,"-",_xlfn.XLOOKUP(B12,july_cfd_trd_5ag!C:C,july_cfd_trd_5ag!G:G)),"-") -> 0.12 | K12: - | L12: - | M12: - | N12: - | O12: - | P12: =_xlfn.XLOOKUP($B12,'[3]All Funds'!$B:$B,'[3]All Funds'!T:T) -> 0.08694745 | Q12: =_xlfn.XLOOKUP($B12,'[3]All Funds'!$B:$B,'[3]All Funds'!U:U) -> 0.148589 | R12: =_xlfn.XLOOKUP($B12,'[3]All Funds'!$B:$B,'[3]All Funds'!V:V) -> 0.12582491 | S12: =_xlfn.XLOOKUP($B12,'[3]All Funds'!$B:$B,'[3]All Funds'!W:W) -> 0.087628204 | T12: =_xlfn.XLOOKUP($B12,'[3]All Funds'!$B:$B,'[3]All Funds'!X:X) -> 0.053387855 | U12: =_xlfn.XLOOKUP($B12,'[3]All Funds'!$B:$B,'[3]All Funds'!Y:Y) -> 0.11694326
A13: Fund Change | B13: LCGFX | C13: =_xlfn.XLOOKUP(B13,'[1]_Funds 2026 04 01'!$B:$B,'[1]_Funds 2026 04 01'!$A:$A) -> William Blair Large Cap Growth I | D13: =_xlfn.XLOOKUP(E13,[2]Sheet1!$D:$D,[2]Sheet1!$B:$B) -> Equity | E13: =_xlfn.XLOOKUP(B13,'[1]_Funds 2026 04 01'!$B:$B,'[1]_Funds 2026 04 01'!$D:$D) -> Large Cap Growth | F13: =IFERROR(IF(_xlfn.XLOOKUP(B13,july_cfd_trd_1co!C:C,july_cfd_trd_1co!G:G)=0,"-",_xlfn.XLOOKUP(B13,july_cfd_trd_1co!C:C,july_cfd_trd_1co!G:G)),"-") -> 0.07 | G13: - | H13: =IFERROR(IF(_xlfn.XLOOKUP(B13,july_cfd_trd_3mo!C:C,july_cfd_trd_3mo!G:G)=0,"-",_xlfn.XLOOKUP(B13,july_cfd_trd_3mo!C:C,july_cfd_trd_3mo!G:G)),"-") -> 0.09 | I13: =IFERROR(IF(_xlfn.XLOOKUP(B13,july_cfd_trd_4ma!C:C,july_cfd_trd_4ma!G:G)=0,"-",_xlfn.XLOOKUP(B13,july_cfd_trd_4ma!C:C,july_cfd_trd_4ma!G:G)),"-") -> 0.15 | J13: =IFERROR(IF(_xlfn.XLOOKUP(B13,july_cfd_trd_5ag!C:C,july_cfd_trd_5ag!G:G)=0,"-",_xlfn.XLOOKUP(B13,july_cfd_trd_5ag!C:C,july_cfd_trd_5ag!G:G)),"-") -> 0.2 | K13: - | L13: - | M13: - | N13: - | O13: - | P13: =_xlfn.XLOOKUP($B13,'[3]All Funds'!$B:$B,'[3]All Funds'!T:T) -> 0.64866044 | Q13: =_xlfn.XLOOKUP($B13,'[3]All Funds'!$B:$B,'[3]All Funds'!U:U) -> 0.61158916 | R13: =_xlfn.XLOOKUP($B13,'[3]All Funds'!$B:$B,'[3]All Funds'!V:V) -> 0.59730141 | S13: =_xlfn.XLOOKUP($B13,'[3]All Funds'!$B:$B,'[3]All Funds'!W:W) -> 0.45472793 | T13: =_xlfn.XLOOKUP($B13,'[3]All Funds'!$B:$B,'[3]All Funds'!X:X) -> 0.28432084 | U13: =_xlfn.XLOOKUP($B13,'[3]All Funds'!$B:$B,'[3]All Funds'!Y:Y) -> 0.68832983
B14: PEQSX | C14: =_xlfn.XLOOKUP(B14,'[1]_Funds 2026 04 01'!$B:$B,'[1]_Funds 2026 04 01'!$A:$A) -> Putnam Large Cap Value R6 | D14: =_xlfn.XLOOKUP(E14,[2]Sheet1!$D:$D,[2]Sheet1!$B:$B) -> Equity | E14: =_xlfn.XLOOKUP(B14,'[1]_Funds 2026 04 01'!$B:$B,'[1]_Funds 2026 04 01'!$D:$D) -> Large Cap Value | F14: =IFERROR(IF(_xlfn.XLOOKUP(B14,july_cfd_trd_1co!C:C,july_cfd_trd_1co!G:G)=0,"-",_xlfn.XLOOKUP(B14,july_cfd_trd_1co!C:C,july_cfd_trd_1co!G:G)),"-") -> 0.08 | G14: - | H14: =IFERROR(IF(_xlfn.XLOOKUP(B14,july_cfd_trd_3mo!C:C,july_cfd_trd_3mo!G:G)=0,"-",_xlfn.XLOOKUP(B14,july_cfd_trd_3mo!C:C,july_cfd_trd_3mo!G:G)),"-") -> 0.06 | I14: =IFERROR(IF(_xlfn.XLOOKUP(B14,july_cfd_trd_4ma!C:C,july_cfd_trd_4ma!G:G)=0,"-",_xlfn.XLOOKUP(B14,july_cfd_trd_4ma!C:C,july_cfd_trd_4ma!G:G)),"-") -> 0.06 | J14: =IFERROR(IF(_xlfn.XLOOKUP(B14,july_cfd_trd_5ag!C:C,july_cfd_trd_5ag!G:G)=0,"-",_xlfn.XLOOKUP(B14,july_cfd_trd_5ag!C:C,july_cfd_trd_5ag!G:G)),"-") -> 0.05 | K14: - | L14: - | M14: - | N14: - | O14: - | P14: =_xlfn.XLOOKUP($B14,'[3]All Funds'!$B:$B,'[3]All Funds'!T:T) -> 0.0044240083 | Q14: =_xlfn.XLOOKUP($B14,'[3]All Funds'!$B:$B,'[3]All Funds'!U:U) -> 0.0078392367 | R14: =_xlfn.XLOOKUP($B14,'[3]All Funds'!$B:$B,'[3]All Funds'!V:V) -> 0.01618291 | S14: =_xlfn.XLOOKUP($B14,'[3]All Funds'!$B:$B,'[3]All Funds'!W:W) -> 0.011394306 | T14: =_xlfn.XLOOKUP($B14,'[3]All Funds'!$B:$B,'[3]All Funds'!X:X) -> 0.0087395368 | U14: =_xlfn.XLOOKUP($B14,'[3]All Funds'!$B:$B,'[3]All Funds'!Y:Y) -> 0.0057038743
B15: RPTTX | C15: =_xlfn.XLOOKUP(B15,'[1]_Funds 2026 04 01'!$B:$B,'[1]_Funds 2026 04 01'!$A:$A) -> T. Rowe Price Diversified Mid Cap Gr I | D15: =_xlfn.XLOOKUP(E15,[2]Sheet1!$D:$D,[2]Sheet1!$B:$B) -> Equity | E15: =_xlfn.XLOOKUP(B15,'[1]_Funds 2026 04 01'!$B:$B,'[1]_Funds 2026 04 01'!$D:$D) -> Mid Cap Growth | F15: =IFERROR(IF(_xlfn.XLOOKUP(B15,july_cfd_trd_1co!C:C,july_cfd_trd_1co!G:G)=0,"-",_xlfn.XLOOKUP(B15,july_cfd_trd_1co!C:C,july_cfd_trd_1co!G:G)),"-") -> - | G15: - | H15: =IFERROR(IF(_xlfn.XLOOKUP(B15,july_cfd_trd_3mo!C:C,july_cfd_trd_3mo!G:G)=0,"-",_xlfn.XLOOKUP(B15,july_cfd_trd_3mo!C:C,july_cfd_trd_3mo!G:G)),"-") -> 0.08 | I15: =IFERROR(IF(_xlfn.XLOOKUP(B15,july_cfd_trd_4ma!C:C,july_cfd_trd_4ma!G:G)=0,"-",_xlfn.XLOOKUP(B15,july_cfd_trd_4ma!C:C,july_cfd_trd_4ma!G:G)),"-") -> 0.11 | J15: =IFERROR(IF(_xlfn.XLOOKUP(B15,july_cfd_trd_5ag!C:C,july_cfd_trd_5ag!G:G)=0,"-",_xlfn.XLOOKUP(B15,july_cfd_trd_5ag!C:C,july_cfd_trd_5ag!G:G)),"-") -> 0.14 | K15: - | L15: - | M15: - | N15: - | O15: - | P15: =_xlfn.XLOOKUP($B15,'[3]All Funds'!$B:$B,'[3]All Funds'!T:T) -> 0.083792796 | Q15: =_xlfn.XLOOKUP($B15,'[3]All Funds'!$B:$B,'[3]All Funds'!U:U) -> 0.05378493 | R15: =_xlfn.XLOOKUP($B15,'[3]All Funds'!$B:$B,'[3]All Funds'!V:V) -> 0.040708906 | S15: =_xlfn.XLOOKUP($B15,'[3]All Funds'!$B:$B,'[3]All Funds'!W:W) -> 0.048973996 | T15: =_xlfn.XLOOKUP($B15,'[3]All Funds'!$B:$B,'[3]All Funds'!X:X) -> 0.07513395 | U15: =_xlfn.XLOOKUP($B15,'[3]All Funds'!$B:$B,'[3]All Funds'!Y:Y) -> 0.12121357
B16: GCASX | C16: =_xlfn.XLOOKUP(B16,'[1]_Funds 2026 04 01'!$B:$B,'[1]_Funds 2026 04 01'!$A:$A) -> Gabelli Small Cap Growth A | D16: =_xlfn.XLOOKUP(E16,[2]Sheet1!$D:$D,[2]Sheet1!$B:$B) -> Equity | E16: =_xlfn.XLOOKUP(B16,'[1]_Funds 2026 04 01'!$B:$B,'[1]_Funds 2026 04 01'!$D:$D) -> Small Cap Blend | F16: =IFERROR(IF(_xlfn.XLOOKUP(B16,july_cfd_trd_1co!C:C,july_cfd_trd_1co!G:G)=0,"-",_xlfn.XLOOKUP(B16,july_cfd_trd_1co!C:C,july_cfd_trd_1co!G:G)),"-") -> - | G16: - | H16: =IFERROR(IF(_xlfn.XLOOKUP(B16,july_cfd_trd_3mo!C:C,july_cfd_trd_3mo!G:G)=0,"-",_xlfn.XLOOKUP(B16,july_cfd_trd_3mo!C:C,july_cfd_trd_3mo!G:G)),"-") -> 0.05 | I16: =IFERROR(IF(_xlfn.XLOOKUP(B16,july_cfd_trd_4ma!C:C,july_cfd_trd_4ma!G:G)=0,"-",_xlfn.XLOOKUP(B16,july_cfd_trd_4ma!C:C,july_cfd_trd_4ma!G:G)),"-") -> 0.08 | J16: =IFERROR(IF(_xlfn.XLOOKUP(B16,july_cfd_trd_5ag!C:C,july_cfd_trd_5ag!G:G)=0,"-",_xlfn.XLOOKUP(B16,july_cfd_trd_5ag!C:C,july_cfd_trd_5ag!G:G)),"-") -> 0.13 | K16: - | L16: - | M16: - | N16: - | O16: - | P16: =_xlfn.XLOOKUP($B16,'[3]All Funds'!$B:$B,'[3]All Funds'!T:T) -> 0.30309722 | Q16: =_xlfn.XLOOKUP($B16,'[3]All Funds'!$B:$B,'[3]All Funds'!U:U) -> 0.30274214 | R16: =_xlfn.XLOOKUP($B16,'[3]All Funds'!$B:$B,'[3]All Funds'!V:V) -> 0.30648634 | S16: =_xlfn.XLOOKUP($B16,'[3]All Funds'!$B:$B,'[3]All Funds'!W:W) -> 0.28314215 | T16: =_xlfn.XLOOKUP($B16,'[3]All Funds'!$B:$B,'[3]All Funds'!X:X) -> 0.24671565 | U16: =_xlfn.XLOOKUP($B16,'[3]All Funds'!$B:$B,'[3]All Funds'!Y:Y) -> 0.47375524
B17: RAPZX | C17: =_xlfn.XLOOKUP(B17,'[1]_Funds 2026 04 01'!$B:$B,'[1]_Funds 2026 04 01'!$A:$A) -> Cohen & Steers Real Assets Z | D17: =_xlfn.XLOOKUP(E17,[2]Sheet1!$D:$D,[2]Sheet1!$B:$B) -> Allocation | E17: =_xlfn.XLOOKUP(B17,'[1]_Funds 2026 04 01'!$B:$B,'[1]_Funds 2026 04 01'!$D:$D) -> Global Moderate Allocation | F17: =IFERROR(IF(_xlfn.XLOOKUP(B17,july_cfd_trd_1co!C:C,july_cfd_trd_1co!G:G)=0,"-",_xlfn.XLOOKUP(B17,july_cfd_trd_1co!C:C,july_cfd_trd_1co!G:G)),"-") -> 0.04 | G17: - | H17: =IFERROR(IF(_xlfn.XLOOKUP(B17,july_cfd_trd_3mo!C:C,july_cfd_trd_3mo!G:G)=0,"-",_xlfn.XLOOKUP(B17,july_cfd_trd_3mo!C:C,july_cfd_trd_3mo!G:G)),"-") -> 0.04 | I17: =IFERROR(IF(_xlfn.XLOOKUP(B17,july_cfd_trd_4ma!C:C,july_cfd_trd_4ma!G:G)=0,"-",_xlfn.XLOOKUP(B17,july_cfd_trd_4ma!C:C,july_cfd_trd_4ma!G:G)),"-") -> 0.04 | J17: =IFERROR(IF(_xlfn.XLOOKUP(B17,july_cfd_trd_5ag!C:C,july_cfd_trd_5ag!G:G)=0,"-",_xlfn.XLOOKUP(B17,july_cfd_trd_5ag!C:C,july_cfd_trd_5ag!G:G)),"-") -> 0.04 | K17: - | L17: - | M17: - | N17: - | O17: - | P17: =_xlfn.XLOOKUP($B17,'[3]All Funds'!$B:$B,'[3]All Funds'!T:T) -> 0.11324977 | Q17: =_xlfn.XLOOKUP($B17,'[3]All Funds'!$B:$B,'[3]All Funds'!U:U) -> 0.24691721 | R17: =_xlfn.XLOOKUP($B17,'[3]All Funds'!$B:$B,'[3]All Funds'!V:V) -> 0.27505122 | S17: =_xlfn.XLOOKUP($B17,'[3]All Funds'!$B:$B,'[3]All Funds'!W:W) -> 0.28885411 | T17: =_xlfn.XLOOKUP($B17,'[3]All Funds'!$B:$B,'[3]All Funds'!X:X) -> 0.32118353 | U17: =_xlfn.XLOOKUP($B17,'[3]All Funds'!$B:$B,'[3]All Funds'!Y:Y) -> 0.028500448
B18: PGLSX | C18: =_xlfn.XLOOKUP(B18,'[1]_Funds 2026 04 01'!$B:$B,'[1]_Funds 2026 04 01'!$A:$A) -> Principal Global Multi-Strategy R-6 | D18: =_xlfn.XLOOKUP(E18,[2]Sheet1!$D:$D,[2]Sheet1!$B:$B) -> Alternatives | E18: =_xlfn.XLOOKUP(B18,'[1]_Funds 2026 04 01'!$B:$B,'[1]_Funds 2026 04 01'!$D:$D) -> Multistrategy | F18: =IFERROR(IF(_xlfn.XLOOKUP(B18,july_cfd_trd_1co!C:C,july_cfd_trd_1co!G:G)=0,"-",_xlfn.XLOOKUP(B18,july_cfd_trd_1co!C:C,july_cfd_trd_1co!G:G)),"-") -> 0.04 | G18: - | H18: =IFERROR(IF(_xlfn.XLOOKUP(B18,july_cfd_trd_3mo!C:C,july_cfd_trd_3mo!G:G)=0,"-",_xlfn.XLOOKUP(B18,july_cfd_trd_3mo!C:C,july_cfd_trd_3mo!G:G)),"-") -> 0.04 | I18: =IFERROR(IF(_xlfn.XLOOKUP(B18,july_cfd_trd_4ma!C:C,july_cfd_trd_4ma!G:G)=0,"-",_xlfn.XLOOKUP(B18,july_cfd_trd_4ma!C:C,july_cfd_trd_4ma!G:G)),"-") -> - | J18: =IFERROR(IF(_xlfn.XLOOKUP(B18,july_cfd_trd_5ag!C:C,july_cfd_trd_5ag!G:G)=0,"-",_xlfn.XLOOKUP(B18,july_cfd_trd_5ag!C:C,july_cfd_trd_5ag!G:G)),"-") -> - | K18: - | L18: - | M18: - | N18: - | O18: - | P18: =_xlfn.XLOOKUP($B18,'[3]All Funds'!$B:$B,'[3]All Funds'!T:T) -> 0.020771231 | Q18: =_xlfn.XLOOKUP($B18,'[3]All Funds'!$B:$B,'[3]All Funds'!U:U) -> 0.023216585 | R18: =_xlfn.XLOOKUP($B18,'[3]All Funds'!$B:$B,'[3]All Funds'!V:V) -> 0.046979058 | S18: =_xlfn.XLOOKUP($B18,'[3]All Funds'!$B:$B,'[3]All Funds'!W:W) -> 0.057499653 | T18: =_xlfn.XLOOKUP($B18,'[3]All Funds'!$B:$B,'[3]All Funds'!X:X) -> 0.12506317 | U18: =_xlfn.XLOOKUP($B18,'[3]All Funds'!$B:$B,'[3]All Funds'!Y:Y) -> 0.016579982
F19: =SUM(F2:F18) -> 1 | G19: =SUM(G2:G18) -> 0 | H19: =SUM(H2:H18) -> 1 | I19: =SUM(I2:I18) -> 1 | J19: =SUM(J2:J18) -> 1 | K19: =SUM(K2:K18) -> 0 | L19: =SUM(L2:L18) -> 0 | M19: =SUM(M2:M18) -> 0 | ... O19: =SUM(O2:O18) -> 0

Sheet july_cfd_trd_1co
A1: Investment | B1: Fees/Trading Rules | C1: Fund ID | D1: Balance | E1: Units | F1: Price | G1: Allocation Percent
A2: American Funds EUPAC R6 | B2: Trade Rules | C2: RERGX | D2: 2992.08 | E2: 46.942 | F2: 63.74 | G2: 0.05
A3: AB Global Bond I | B3: Trade Rules | C3: ANAIX | D3: 3458.37 | E3: 520.056 | F3: 6.65 | G3: 0.06
A4: Cohen & Steers Real Assets Z | B4: Trade Rules | C4: RAPZX | D4: 2464.28 | E4: 199.215 | F4: 12.37 | G4: 0.04
A5: AllianceBern High Income I | B5: Trade Rules | C5: AGDIX | D5: 2954.74 | E5: 432.61 | F5: 6.83 | G5: 0.05
A6: American Funds Bond Fund of Amer F3 | B6: Trade Rules | C6: BFFAX | D6: 5747.28 | E6: 532.155 | F6: 10.8 | G6: 0.1
A7: Dodge & Cox Income Fund | B7: Trade Rules | C7: DODIX | D7: 8578.03 | E7: 700.82 | F7: 12.24 | G7: 0.15
A8: American Funds US Government Sec R6 | B8: Trade Rules | C8: RGVGX | D8: 8571.73 | E8: 755.885 | F8: 11.34 | G8: 0.15
A9: William Blair Large Cap Growth I | B9: Trade Rules | C9: LCGFX | D9: 4345.06 | E9: 139.22 | F9: 31.21 | G9: 0.07
A10: Putnam Large Cap Value R6 | B10: Trade Rules | C10: PEQSX | D10: 4907.55 | E10: 110.208 | F10: 44.53 | G10: 0.08
A11: American Funds Multi-Sector Income R-6 | B11: Trade Rules | C11: RMDUX | D11: 6389.36 | E11: 709.142 | F11: 9.01 | G11: 0.11
A12: Principal Global Multi-Strategy R-6 | B12: Trade Rules | C12: PGLSX | D12: 2426.89 | E12: 193.996 | F12: 12.51 | G12: 0.04
A13: Fidelity Short-Term Bond Fund | B13: Trade Rules | C13: FSHBX | D13: 5921.86 | E13: 711.762 | F13: 8.32 | G13: 0.1

Sheet Sheet4

Sheet july_cfd_trd_3mo
A1: Investment | B1: Fees/Trading Rules | C1: Fund ID | D1: Balance | E1: Units | F1: Price | G1: Allocation Percent
A2: GQG Partners Emerging Markets Equity I | B2: Trade Rules | C2: GQGIX | D2: 4124.6 | E2: 211.627 | F2: 19.49 | G2: 0.05
A3: American Funds EUPAC R6 | B3: Trade Rules | C3: RERGX | D3: 10415.81 | E3: 163.411 | F3: 63.74 | G3: 0.13
A4: AB Global Bond I | B4: Trade Rules | C4: ANAIX | D4: 3855.77 | E4: 579.815 | F4: 6.65 | G4: 0.05
A5: Cohen & Steers Real Assets Z | B5: Trade Rules | C5: RAPZX | D5: 3242.14 | E5: 262.097 | F5: 12.37 | G5: 0.04
A6: AllianceBern High Income I | B6: Trade Rules | C6: AGDIX | D6: 3932.44 | E6: 575.758 | F6: 6.83 | G6: 0.05
A7: American Funds Bond Fund of Amer F3 | B7: Trade Rules | C7: BFFAX | D7: 6155.77 | E7: 569.979 | F7: 10.8 | G7: 0.08
A8: Dodge & Cox Income Fund | B8: Trade Rules | C8: DODIX | D8: 7662.31 | E8: 626.004 | F8: 12.24 | G8: 0.1
A9: American Funds US Government Sec R6 | B9: Trade Rules | C9: RGVGX | D9: 3826.93 | E9: 337.471 | F9: 11.34 | G9: 0.05
A10: Invesco S&P 500® Quality ETF | B10: Trade Rules | C10: SPHQ | D10: 4576.25 | E10: 54.324 | F10: 84.24 | G10: 0.06
A11: William Blair Large Cap Growth I | B11: Trade Rules | C11: LCGFX | D11: 7361.59 | E11: 235.873 | F11: 31.21 | G11: 0.09
A12: Putnam Large Cap Value R6 | B12: Trade Rules | C12: PEQSX | D12: 4865.74 | E12: 109.269 | F12: 44.53 | G12: 0.06
A13: T. Rowe Price Diversified Mid Cap Gr I | B13: Trade Rules | C13: RPTTX | D13: 6191.85 | E13: 127.825 | F13: 48.44 | G13: 0.08
... A16: Gabelli Small Cap Growth A | B16: Trade Rules | C16: GCASX | D16: 3785.67 | E16: 76.571 | F16: 49.44 | G16: 0.05

Sheet july_cfd_trd_4ma
A1: Investment | B1: Fees/Trading Rules | C1: Fund ID | D1: Balance | E1: Units | F1: Price | G1: Allocation Percent
A2: GQG Partners Emerging Markets Equity I | B2: Trade Rules | C2: GQGIX | D2: 64240.25 | E2: 3296.062 | F2: 19.49 | G2: 0.08
A3: American Funds EUPAC R6 | B3: Trade Rules | C3: RERGX | D3: 131081.99 | E3: 2056.511 | F3: 63.74 | G3: 0.17
A4: AB Global Bond I | B4: Trade Rules | C4: ANAIX | D4: 37159.37 | E4: 5587.873 | F4: 6.65 | G4: 0.05
A5: Cohen & Steers Real Assets Z | B5: Trade Rules | C5: RAPZX | D5: 31653.29 | E5: 2558.875 | F5: 12.37 | G5: 0.04
A6: American Funds Bond Fund of Amer F3 | B6: Trade Rules | C6: BFFAX | D6: 37064.18 | E6: 3431.868 | F6: 10.8 | G6: 0.05
A7: Dodge & Cox Income Fund | B7: Trade Rules | C7: DODIX | D7: 36873.42 | E7: 3012.534 | F7: 12.24 | G7: 0.05
A8: Invesco S&P 500® Quality ETF | B8: Trade Rules | C8: SPHQ | D8: 80126.14 | E8: 951.165 | F8: 84.24 | G8: 0.11
A9: William Blair Large Cap Growth I | B9: Trade Rules | C9: LCGFX | D9: 119703.05 | E9: 3835.406 | F9: 31.21 | G9: 0.15
A10: Putnam Large Cap Value R6 | B10: Trade Rules | C10: PEQSX | D10: 47315.96 | E10: 1062.564 | F10: 44.53 | G10: 0.06
A11: T. Rowe Price Diversified Mid Cap Gr I | B11: Trade Rules | C11: RPTTX | D11: 81346.76 | E11: 1679.33 | F11: 48.44 | G11: 0.11
A12: American Funds Multi-Sector Income R-6 | B12: Trade Rules | C12: RMDUX | D12: 37437.44 | E12: 4155.101 | F12: 9.01 | G12: 0.05
A13: Gabelli Small Cap Growth A | B13: Trade Rules | C13: GCASX | D13: 58072.05 | E13: 1174.597 | F13: 49.44 | G13: 0.08

Sheet july_cfd_trd_5ag
A1: Investment | B1: Fees/Trading Rules | C1: Fund ID | D1: Balance | E1: Units | F1: Price | G1: Allocation Percent
A2: GQG Partners Emerging Markets Equity I | B2: Trade Rules | C2: GQGIX | D2: 115148.75 | E2: 5908.094 | F2: 19.49 | G2: 0.11
A3: American Funds EUPAC R6 | B3: Trade Rules | C3: RERGX | D3: 210916.87 | E3: 3309.019 | F3: 63.74 | G3: 0.21
A4: Cohen & Steers Real Assets Z | B4: Trade Rules | C4: RAPZX | D4: 41267.53 | E4: 3336.095 | F4: 12.37 | G4: 0.04
A5: Invesco S&P 500® Quality ETF | B5: Trade Rules | C5: SPHQ | D5: 113757.46 | E5: 1350.397 | F5: 84.24 | G5: 0.12
A6: William Blair Large Cap Growth I | B6: Trade Rules | C6: LCGFX | D6: 208090.59 | E6: 6667.432 | F6: 31.21 | G6: 0.2
A7: Putnam Large Cap Value R6 | B7: Trade Rules | C7: PEQSX | D7: 51410.76 | E7: 1154.52 | F7: 44.53 | G7: 0.05
A8: T. Rowe Price Diversified Mid Cap Gr I | B8: Trade Rules | C8: RPTTX | D8: 134736.88 | E8: 2781.52 | F8: 48.44 | G8: 0.14
A9: Gabelli Small Cap Growth A | B9: Trade Rules | C9: GCASX | D9: 122863.66 | E9: 2485.106 | F9: 49.44 | G9: 0.13

Sheet july_cfd_bfv
A1: Ticker | B1: Name | C1: Class | D1: Category | E1: CO | F1: MC | G1: MO | H1: MA | I1: AG | J1: ST (3Mo) | K1: SMT (6Mo) | L1: MT (12Mo) | M1: LT (18Mo) | N1: LT2 (2.5-3.0Y) | O1: 46112
A2: GGBFX | B2: =_xlfn.XLOOKUP(A2,'[1]_Funds 2026 04 01'!$B:$B,'[1]_Funds 2026 04 01'!$A:$A) -> GuideStone Funds Global Bond Investor | C2: =_xlfn.XLOOKUP(D2,[2]Sheet1!$D:$D,[2]Sheet1!$B:$B) -> Fixed Income | D2: =_xlfn.XLOOKUP(A2,'[1]_Funds 2026 04 01'!$B:$B,'[1]_Funds 2026 04 01'!$D:$D) -> Global Fixed Income | E2: =IFERROR(IF(_xlfn.XLOOKUP(A2,july_cfd_bfv_1co!C:C,july_cfd_bfv_1co!G:G)=0,"-",_xlfn.XLOOKUP(A2,july_cfd_bfv_1co!C:C,july_cfd_bfv_1co!G:G)),"-") -> 0.07 | F2: - | G2: =IFERROR(IF(_xlfn.XLOOKUP(A2,july_cfd_bfv_3mo!C:C,july_cfd_bfv_3mo!G:G)=0,"-",_xlfn.XLOOKUP(A2,july_cfd_bfv_3mo!C:C,july_cfd_bfv_3mo!G:G)),"-") -> 0.05 | H2: =IFERROR(IF(_xlfn.XLOOKUP(A2,july_cfd_bfv_4ma!C:C,july_cfd_bfv_4ma!G:G)=0,"-",_xlfn.XLOOKUP(A2,july_cfd_bfv_4ma!C:C,july_cfd_bfv_4ma!G:G)),"-") -> 0.05 | I2: =IFERROR(IF(_xlfn.XLOOKUP(A2,july_cfd_bfv_5ag!C:C,july_cfd_bfv_5ag!G:G)=0,"-",_xlfn.XLOOKUP(A2,july_cfd_bfv_5ag!C:C,july_cfd_bfv_5ag!G:G)),"-") -> - | J2: =_xlfn.XLOOKUP($A2,'[3]All Funds'!$B:$B,'[3]All Funds'!T:T) -> 0.42412997 | K2: =_xlfn.XLOOKUP($A2,'[3]All Funds'!$B:$B,'[3]All Funds'!U:U) -> 0.45172729 | L2: =_xlfn.XLOOKUP($A2,'[3]All Funds'!$B:$B,'[3]All Funds'!V:V) -> 0.45870407 | M2: =_xlfn.XLOOKUP($A2,'[3]All Funds'!$B:$B,'[3]All Funds'!W:W) -> 0.47963913 | N2: =_xlfn.XLOOKUP($A2,'[3]All Funds'!$B:$B,'[3]All Funds'!X:X) -> 0.46827462 | O2: =_xlfn.XLOOKUP($A2,'[3]All Funds'!$B:$B,'[3]All Funds'!Y:Y) -> 0.46289817
A3: TPHIX | B3: =_xlfn.XLOOKUP(A3,'[1]_Funds 2026 04 01'!$B:$B,'[1]_Funds 2026 04 01'!$A:$A) -> Timothy Plan High Yield Bond I | C3: =_xlfn.XLOOKUP(D3,[2]Sheet1!$D:$D,[2]Sheet1!$B:$B) -> Fixed Income | D3: =_xlfn.XLOOKUP(A3,'[1]_Funds 2026 04 01'!$B:$B,'[1]_Funds 2026 04 01'!$D:$D) -> High Yield | E3: =IFERROR(IF(_xlfn.XLOOKUP(A3,july_cfd_bfv_1co!C:C,july_cfd_bfv_1co!G:G)=0,"-",_xlfn.XLOOKUP(A3,july_cfd_bfv_1co!C:C,july_cfd_bfv_1co!G:G)),"-") -> 0.05 | F3: - | G3: =IFERROR(IF(_xlfn.XLOOKUP(A3,july_cfd_bfv_3mo!C:C,july_cfd_bfv_3mo!G:G)=0,"-",_xlfn.XLOOKUP(A3,july_cfd_bfv_3mo!C:C,july_cfd_bfv_3mo!G:G)),"-") -> 0.05 | H3: =IFERROR(IF(_xlfn.XLOOKUP(A3,july_cfd_bfv_4ma!C:C,july_cfd_bfv_4ma!G:G)=0,"-",_xlfn.XLOOKUP(A3,july_cfd_bfv_4ma!C:C,july_cfd_bfv_4ma!G:G)),"-") -> - | I3: =IFERROR(IF(_xlfn.XLOOKUP(A3,july_cfd_bfv_5ag!C:C,july_cfd_bfv_5ag!G:G)=0,"-",_xlfn.XLOOKUP(A3,july_cfd_bfv_5ag!C:C,july_cfd_bfv_5ag!G:G)),"-") -> - | J3: =_xlfn.XLOOKUP($A3,'[3]All Funds'!$B:$B,'[3]All Funds'!T:T) -> 0.5485353 | K3: =_xlfn.XLOOKUP($A3,'[3]All Funds'!$B:$B,'[3]All Funds'!U:U) -> 0.53303308 | L3: =_xlfn.XLOOKUP($A3,'[3]All Funds'!$B:$B,'[3]All Funds'!V:V) -> 0.54383861 | M3: =_xlfn.XLOOKUP($A3,'[3]All Funds'!$B:$B,'[3]All Funds'!W:W) -> 0.46404691 | N3: =_xlfn.XLOOKUP($A3,'[3]All Funds'!$B:$B,'[3]All Funds'!X:X) -> 0.45672118 | O3: =_xlfn.XLOOKUP($A3,'[3]All Funds'!$B:$B,'[3]All Funds'!Y:Y) -> 0.54947264
A4: TPFIX | B4: =_xlfn.XLOOKUP(A4,'[1]_Funds 2026 04 01'!$B:$B,'[1]_Funds 2026 04 01'!$A:$A) -> Timothy Plan Fixed Income I | C4: =_xlfn.XLOOKUP(D4,[2]Sheet1!$D:$D,[2]Sheet1!$B:$B) -> Fixed Income | D4: =_xlfn.XLOOKUP(A4,'[1]_Funds 2026 04 01'!$B:$B,'[1]_Funds 2026 04 01'!$D:$D) -> Intermediate Term Bond (Core) | E4: =IFERROR(IF(_xlfn.XLOOKUP(A4,july_cfd_bfv_1co!C:C,july_cfd_bfv_1co!G:G)=0,"-",_xlfn.XLOOKUP(A4,july_cfd_bfv_1co!C:C,july_cfd_bfv_1co!G:G)),"-") -> 0.16 | F4: - | G4: =IFERROR(IF(_xlfn.XLOOKUP(A4,july_cfd_bfv_3mo!C:C,july_cfd_bfv_3mo!G:G)=0,"-",_xlfn.XLOOKUP(A4,july_cfd_bfv_3mo!C:C,july_cfd_bfv_3mo!G:G)),"-") -> 0.12 | H4: =IFERROR(IF(_xlfn.XLOOKUP(A4,july_cfd_bfv_4ma!C:C,july_cfd_bfv_4ma!G:G)=0,"-",_xlfn.XLOOKUP(A4,july_cfd_bfv_4ma!C:C,july_cfd_bfv_4ma!G:G)),"-") -> 0.07 | I4: =IFERROR(IF(_xlfn.XLOOKUP(A4,july_cfd_bfv_5ag!C:C,july_cfd_bfv_5ag!G:G)=0,"-",_xlfn.XLOOKUP(A4,july_cfd_bfv_5ag!C:C,july_cfd_bfv_5ag!G:G)),"-") -> - | J4: =_xlfn.XLOOKUP($A4,'[3]All Funds'!$B:$B,'[3]All Funds'!T:T) -> 0.75645086 | K4: =_xlfn.XLOOKUP($A4,'[3]All Funds'!$B:$B,'[3]All Funds'!U:U) -> 0.78355532 | L4: =_xlfn.XLOOKUP($A4,'[3]All Funds'!$B:$B,'[3]All Funds'!V:V) -> 0.7840684 | M4: =_xlfn.XLOOKUP($A4,'[3]All Funds'!$B:$B,'[3]All Funds'!W:W) -> 0.79085864 | N4: =_xlfn.XLOOKUP($A4,'[3]All Funds'!$B:$B,'[3]All Funds'!X:X) -> 0.74760463 | O4: =_xlfn.XLOOKUP($A4,'[3]All Funds'!$B:$B,'[3]All Funds'!Y:Y) -> 0.71025967
A5: RGVGX | B5: =_xlfn.XLOOKUP(A5,'[1]_Funds 2026 04 01'!$B:$B,'[1]_Funds 2026 04 01'!$A:$A) -> American Funds US Government Sec R6 | C5: =_xlfn.XLOOKUP(D5,[2]Sheet1!$D:$D,[2]Sheet1!$B:$B) -> Fixed Income | D5: =_xlfn.XLOOKUP(A5,'[1]_Funds 2026 04 01'!$B:$B,'[1]_Funds 2026 04 01'!$D:$D) -> Intermediate Term Government | E5: =IFERROR(IF(_xlfn.XLOOKUP(A5,july_cfd_bfv_1co!C:C,july_cfd_bfv_1co!G:G)=0,"-",_xlfn.XLOOKUP(A5,july_cfd_bfv_1co!C:C,july_cfd_bfv_1co!G:G)),"-") -> 0.15 | F5: - | G5: =IFERROR(IF(_xlfn.XLOOKUP(A5,july_cfd_bfv_3mo!C:C,july_cfd_bfv_3mo!G:G)=0,"-",_xlfn.XLOOKUP(A5,july_cfd_bfv_3mo!C:C,july_cfd_bfv_3mo!G:G)),"-") -> 0.05 | H5: =IFERROR(IF(_xlfn.XLOOKUP(A5,july_cfd_bfv_4ma!C:C,july_cfd_bfv_4ma!G:G)=0,"-",_xlfn.XLOOKUP(A5,july_cfd_bfv_4ma!C:C,july_cfd_bfv_4ma!G:G)),"-") -> - | I5: =IFERROR(IF(_xlfn.XLOOKUP(A5,july_cfd_bfv_5ag!C:C,july_cfd_bfv_5ag!G:G)=0,"-",_xlfn.XLOOKUP(A5,july_cfd_bfv_5ag!C:C,july_cfd_bfv_5ag!G:G)),"-") -> - | J5: =_xlfn.XLOOKUP($A5,'[3]All Funds'!$B:$B,'[3]All Funds'!T:T) -> 0.033837554 | K5: =_xlfn.XLOOKUP($A5,'[3]All Funds'!$B:$B,'[3]All Funds'!U:U) -> 0.030426149 | L5: =_xlfn.XLOOKUP($A5,'[3]All Funds'!$B:$B,'[3]All Funds'!V:V) -> 0.028381043 | M5: =_xlfn.XLOOKUP($A5,'[3]All Funds'!$B:$B,'[3]All Funds'!W:W) -> 0.035999199 | N5: =_xlfn.XLOOKUP($A5,'[3]All Funds'!$B:$B,'[3]All Funds'!X:X) -> 0.074252673 | O5: =_xlfn.XLOOKUP($A5,'[3]All Funds'!$B:$B,'[3]All Funds'!Y:Y) -> 0.033727678
A6: KCLSX | B6: =_xlfn.XLOOKUP(A6,'[1]_Funds 2026 04 01'!$B:$B,'[1]_Funds 2026 04 01'!$A:$A) -> Knights of Columbus Limited Duration S | C6: =_xlfn.XLOOKUP(D6,[2]Sheet1!$D:$D,[2]Sheet1!$B:$B) -> Fixed Income | D6: =_xlfn.XLOOKUP(A6,'[1]_Funds 2026 04 01'!$B:$B,'[1]_Funds 2026 04 01'!$D:$D) -> Short Term Bond | E6: =IFERROR(IF(_xlfn.XLOOKUP(A6,july_cfd_bfv_1co!C:C,july_cfd_bfv_1co!G:G)=0,"-",_xlfn.XLOOKUP(A6,july_cfd_bfv_1co!C:C,july_cfd_bfv_1co!G:G)),"-") -> 0.1 | F6: - | G6: =IFERROR(IF(_xlfn.XLOOKUP(A6,july_cfd_bfv_3mo!C:C,july_cfd_bfv_3mo!G:G)=0,"-",_xlfn.XLOOKUP(A6,july_cfd_bfv_3mo!C:C,july_cfd_bfv_3mo!G:G)),"-") -> - | H6: =IFERROR(IF(_xlfn.XLOOKUP(A6,july_cfd_bfv_4ma!C:C,july_cfd_bfv_4ma!G:G)=0,"-",_xlfn.XLOOKUP(A6,july_cfd_bfv_4ma!C:C,july_cfd_bfv_4ma!G:G)),"-") -> - | I6: =IFERROR(IF(_xlfn.XLOOKUP(A6,july_cfd_bfv_5ag!C:C,july_cfd_bfv_5ag!G:G)=0,"-",_xlfn.XLOOKUP(A6,july_cfd_bfv_5ag!C:C,july_cfd_bfv_5ag!G:G)),"-") -> - | J6: =_xlfn.XLOOKUP($A6,'[3]All Funds'!$B:$B,'[3]All Funds'!T:T) -> 0.63760058 | K6: =_xlfn.XLOOKUP($A6,'[3]All Funds'!$B:$B,'[3]All Funds'!U:U) -> 0.64231592 | L6: =_xlfn.XLOOKUP($A6,'[3]All Funds'!$B:$B,'[3]All Funds'!V:V) -> 0.60577025 | M6: =_xlfn.XLOOKUP($A6,'[3]All Funds'!$B:$B,'[3]All Funds'!W:W) -> 0.59265501 | N6: =_xlfn.XLOOKUP($A6,'[3]All Funds'!$B:$B,'[3]All Funds'!X:X) -> 0.55214674 | O6: =_xlfn.XLOOKUP($A6,'[3]All Funds'!$B:$B,'[3]All Funds'!Y:Y) -> 0.63070342
A7: AVEFX | B7: =_xlfn.XLOOKUP(A7,'[1]_Funds 2026 04 01'!$B:$B,'[1]_Funds 2026 04 01'!$A:$A) -> Ave Maria Bond | C7: =_xlfn.XLOOKUP(D7,[2]Sheet1!$D:$D,[2]Sheet1!$B:$B) -> Allocation | D7: =_xlfn.XLOOKUP(A7,'[1]_Funds 2026 04 01'!$B:$B,'[1]_Funds 2026 04 01'!$D:$D) -> Conservative Allocation | E7: =IFERROR(IF(_xlfn.XLOOKUP(A7,july_cfd_bfv_1co!C:C,july_cfd_bfv_1co!G:G)=0,"-",_xlfn.XLOOKUP(A7,july_cfd_bfv_1co!C:C,july_cfd_bfv_1co!G:G)),"-") -> 0.12 | F7: - | G7: =IFERROR(IF(_xlfn.XLOOKUP(A7,july_cfd_bfv_3mo!C:C,july_cfd_bfv_3mo!G:G)=0,"-",_xlfn.XLOOKUP(A7,july_cfd_bfv_3mo!C:C,july_cfd_bfv_3mo!G:G)),"-") -> 0.07 | H7: =IFERROR(IF(_xlfn.XLOOKUP(A7,july_cfd_bfv_4ma!C:C,july_cfd_bfv_4ma!G:G)=0,"-",_xlfn.XLOOKUP(A7,july_cfd_bfv_4ma!C:C,july_cfd_bfv_4ma!G:G)),"-") -> 0.07 | I7: =IFERROR(IF(_xlfn.XLOOKUP(A7,july_cfd_bfv_5ag!C:C,july_cfd_bfv_5ag!G:G)=0,"-",_xlfn.XLOOKUP(A7,july_cfd_bfv_5ag!C:C,july_cfd_bfv_5ag!G:G)),"-") -> - | J7: =_xlfn.XLOOKUP($A7,'[3]All Funds'!$B:$B,'[3]All Funds'!T:T) -> 0.34308648 | K7: =_xlfn.XLOOKUP($A7,'[3]All Funds'!$B:$B,'[3]All Funds'!U:U) -> 0.41229275 | L7: =_xlfn.XLOOKUP($A7,'[3]All Funds'!$B:$B,'[3]All Funds'!V:V) -> 0.32749737 | M7: =_xlfn.XLOOKUP($A7,'[3]All Funds'!$B:$B,'[3]All Funds'!W:W) -> 0.22715843 | N7: =_xlfn.XLOOKUP($A7,'[3]All Funds'!$B:$B,'[3]All Funds'!X:X) -> 0.18879933 | O7: =_xlfn.XLOOKUP($A7,'[3]All Funds'!$B:$B,'[3]All Funds'!Y:Y) -> 0.45512481
A8: ETIMX | B8: =_xlfn.XLOOKUP(A8,'[1]_Funds 2026 04 01'!$B:$B,'[1]_Funds 2026 04 01'!$A:$A) -> Eventide Balanced Fund Class I | C8: =_xlfn.XLOOKUP(D8,[2]Sheet1!$D:$D,[2]Sheet1!$B:$B) -> Allocation | D8: =_xlfn.XLOOKUP(A8,'[1]_Funds 2026 04 01'!$B:$B,'[1]_Funds 2026 04 01'!$D:$D) -> Moderate Allocation | E8: =IFERROR(IF(_xlfn.XLOOKUP(A8,july_cfd_bfv_1co!C:C,july_cfd_bfv_1co!G:G)=0,"-",_xlfn.XLOOKUP(A8,july_cfd_bfv_1co!C:C,july_cfd_bfv_1co!G:G)),"-") -> 0.1 | F8: - | G8: =IFERROR(IF(_xlfn.XLOOKUP(A8,july_cfd_bfv_3mo!C:C,july_cfd_bfv_3mo!G:G)=0,"-",_xlfn.XLOOKUP(A8,july_cfd_bfv_3mo!C:C,july_cfd_bfv_3mo!G:G)),"-") -> 0.05 | H8: =IFERROR(IF(_xlfn.XLOOKUP(A8,july_cfd_bfv_4ma!C:C,july_cfd_bfv_4ma!G:G)=0,"-",_xlfn.XLOOKUP(A8,july_cfd_bfv_4ma!C:C,july_cfd_bfv_4ma!G:G)),"-") -> - | I8: =IFERROR(IF(_xlfn.XLOOKUP(A8,july_cfd_bfv_5ag!C:C,july_cfd_bfv_5ag!G:G)=0,"-",_xlfn.XLOOKUP(A8,july_cfd_bfv_5ag!C:C,july_cfd_bfv_5ag!G:G)),"-") -> - | J8: =_xlfn.XLOOKUP($A8,'[3]All Funds'!$B:$B,'[3]All Funds'!T:T) -> 0.72669832 | K8: =_xlfn.XLOOKUP($A8,'[3]All Funds'!$B:$B,'[3]All Funds'!U:U) -> 0.77275827 | L8: =_xlfn.XLOOKUP($A8,'[3]All Funds'!$B:$B,'[3]All Funds'!V:V) -> 0.72840253 | M8: =_xlfn.XLOOKUP($A8,'[3]All Funds'!$B:$B,'[3]All Funds'!W:W) -> 0.57003898 | N8: =_xlfn.XLOOKUP($A8,'[3]All Funds'!$B:$B,'[3]All Funds'!X:X) -> 0.44425325 | O8: =_xlfn.XLOOKUP($A8,'[3]All Funds'!$B:$B,'[3]All Funds'!Y:Y) -> 0.62438991
A9: GEMZX | B9: =_xlfn.XLOOKUP(A9,'[1]_Funds 2026 04 01'!$B:$B,'[1]_Funds 2026 04 01'!$A:$A) -> GuideStone Funds Emerging Mkts Eq Inv | C9: =_xlfn.XLOOKUP(D9,[2]Sheet1!$D:$D,[2]Sheet1!$B:$B) -> Equity | D9: =_xlfn.XLOOKUP(A9,'[1]_Funds 2026 04 01'!$B:$B,'[1]_Funds 2026 04 01'!$D:$D) -> Emerging Markets Equity | E9: =IFERROR(IF(_xlfn.XLOOKUP(A9,july_cfd_bfv_1co!C:C,july_cfd_bfv_1co!G:G)=0,"-",_xlfn.XLOOKUP(A9,july_cfd_bfv_1co!C:C,july_cfd_bfv_1co!G:G)),"-") -> - | F9: - | G9: =IFERROR(IF(_xlfn.XLOOKUP(A9,july_cfd_bfv_3mo!C:C,july_cfd_bfv_3mo!G:G)=0,"-",_xlfn.XLOOKUP(A9,july_cfd_bfv_3mo!C:C,july_cfd_bfv_3mo!G:G)),"-") -> 0.04 | H9: =IFERROR(IF(_xlfn.XLOOKUP(A9,july_cfd_bfv_4ma!C:C,july_cfd_bfv_4ma!G:G)=0,"-",_xlfn.XLOOKUP(A9,july_cfd_bfv_4ma!C:C,july_cfd_bfv_4ma!G:G)),"-") -> 0.07 | I9: =IFERROR(IF(_xlfn.XLOOKUP(A9,july_cfd_bfv_5ag!C:C,july_cfd_bfv_5ag!G:G)=0,"-",_xlfn.XLOOKUP(A9,july_cfd_bfv_5ag!C:C,july_cfd_bfv_5ag!G:G)),"-") -> 0.11 | J9: =_xlfn.XLOOKUP($A9,'[3]All Funds'!$B:$B,'[3]All Funds'!T:T) -> 0.58744703 | K9: =_xlfn.XLOOKUP($A9,'[3]All Funds'!$B:$B,'[3]All Funds'!U:U) -> 0.57083219 | L9: =_xlfn.XLOOKUP($A9,'[3]All Funds'!$B:$B,'[3]All Funds'!V:V) -> 0.55764802 | M9: =_xlfn.XLOOKUP($A9,'[3]All Funds'!$B:$B,'[3]All Funds'!W:W) -> 0.51582216 | N9: =_xlfn.XLOOKUP($A9,'[3]All Funds'!$B:$B,'[3]All Funds'!X:X) -> 0.51333974 | O9: =_xlfn.XLOOKUP($A9,'[3]All Funds'!$B:$B,'[3]All Funds'!Y:Y) -> 0.59737155
A10: GIEZX | B10: =_xlfn.XLOOKUP(A10,'[1]_Funds 2026 04 01'!$B:$B,'[1]_Funds 2026 04 01'!$A:$A) -> GuideStone Funds International Eq Inv | C10: =_xlfn.XLOOKUP(D10,[2]Sheet1!$D:$D,[2]Sheet1!$B:$B) -> Equity | D10: =_xlfn.XLOOKUP(A10,'[1]_Funds 2026 04 01'!$B:$B,'[1]_Funds 2026 04 01'!$D:$D) -> International Large Cap Blend | E10: =IFERROR(IF(_xlfn.XLOOKUP(A10,july_cfd_bfv_1co!C:C,july_cfd_bfv_1co!G:G)=0,"-",_xlfn.XLOOKUP(A10,july_cfd_bfv_1co!C:C,july_cfd_bfv_1co!G:G)),"-") -> 0.05 | F10: - | G10: =IFERROR(IF(_xlfn.XLOOKUP(A10,july_cfd_bfv_3mo!C:C,july_cfd_bfv_3mo!G:G)=0,"-",_xlfn.XLOOKUP(A10,july_cfd_bfv_3mo!C:C,july_cfd_bfv_3mo!G:G)),"-") -> 0.13 | H10: =IFERROR(IF(_xlfn.XLOOKUP(A10,july_cfd_bfv_4ma!C:C,july_cfd_bfv_4ma!G:G)=0,"-",_xlfn.XLOOKUP(A10,july_cfd_bfv_4ma!C:C,july_cfd_bfv_4ma!G:G)),"-") -> 0.18 | I10: =IFERROR(IF(_xlfn.XLOOKUP(A10,july_cfd_bfv_5ag!C:C,july_cfd_bfv_5ag!G:G)=0,"-",_xlfn.XLOOKUP(A10,july_cfd_bfv_5ag!C:C,july_cfd_bfv_5ag!G:G)),"-") -> 0.19 | J10: =_xlfn.XLOOKUP($A10,'[3]All Funds'!$B:$B,'[3]All Funds'!T:T) -> 0.66562754 | K10: =_xlfn.XLOOKUP($A10,'[3]All Funds'!$B:$B,'[3]All Funds'!U:U) -> 0.64194456 | L10: =_xlfn.XLOOKUP($A10,'[3]All Funds'!$B:$B,'[3]All Funds'!V:V) -> 0.512886 | M10: =_xlfn.XLOOKUP($A10,'[3]All Funds'!$B:$B,'[3]All Funds'!W:W) -> 0.43979212 | N10: =_xlfn.XLOOKUP($A10,'[3]All Funds'!$B:$B,'[3]All Funds'!X:X) -> 0.39206491 | O10: =_xlfn.XLOOKUP($A10,'[3]All Funds'!$B:$B,'[3]All Funds'!Y:Y) -> 0.67974103
A11: GEQZX | B11: =_xlfn.XLOOKUP(A11,'[1]_Funds 2026 04 01'!$B:$B,'[1]_Funds 2026 04 01'!$A:$A) -> GuideStone Funds Equity Index Investor | C11: =_xlfn.XLOOKUP(D11,[2]Sheet1!$D:$D,[2]Sheet1!$B:$B) -> Equity | D11: =_xlfn.XLOOKUP(A11,'[1]_Funds 2026 04 01'!$B:$B,'[1]_Funds 2026 04 01'!$D:$D) -> Large Cap Blend | E11: =IFERROR(IF(_xlfn.XLOOKUP(A11,july_cfd_bfv_1co!C:C,july_cfd_bfv_1co!G:G)=0,"-",_xlfn.XLOOKUP(A11,july_cfd_bfv_1co!C:C,july_cfd_bfv_1co!G:G)),"-") -> 0.05 | F11: - | G11: =IFERROR(IF(_xlfn.XLOOKUP(A11,july_cfd_bfv_3mo!C:C,july_cfd_bfv_3mo!G:G)=0,"-",_xlfn.XLOOKUP(A11,july_cfd_bfv_3mo!C:C,july_cfd_bfv_3mo!G:G)),"-") -> 0.06 | H11: =IFERROR(IF(_xlfn.XLOOKUP(A11,july_cfd_bfv_4ma!C:C,july_cfd_bfv_4ma!G:G)=0,"-",_xlfn.XLOOKUP(A11,july_cfd_bfv_4ma!C:C,july_cfd_bfv_4ma!G:G)),"-") -> 0.12 | I11: =IFERROR(IF(_xlfn.XLOOKUP(A11,july_cfd_bfv_5ag!C:C,july_cfd_bfv_5ag!G:G)=0,"-",_xlfn.XLOOKUP(A11,july_cfd_bfv_5ag!C:C,july_cfd_bfv_5ag!G:G)),"-") -> 0.18 | J11: =_xlfn.XLOOKUP($A11,'[3]All Funds'!$B:$B,'[3]All Funds'!T:T) -> 0.34079601 | K11: =_xlfn.XLOOKUP($A11,'[3]All Funds'!$B:$B,'[3]All Funds'!U:U) -> 0.30964687 | L11: =_xlfn.XLOOKUP($A11,'[3]All Funds'!$B:$B,'[3]All Funds'!V:V) -> 0.32481264 | M11: =_xlfn.XLOOKUP($A11,'[3]All Funds'!$B:$B,'[3]All Funds'!W:W) -> 0.35381009 | N11: =_xlfn.XLOOKUP($A11,'[3]All Funds'!$B:$B,'[3]All Funds'!X:X) -> 0.37482505 | O11: =_xlfn.XLOOKUP($A11,'[3]All Funds'!$B:$B,'[3]All Funds'!Y:Y) -> 0.37492247
A12: MMDEX | B12: =_xlfn.XLOOKUP(A12,'[1]_Funds 2026 04 01'!$B:$B,'[1]_Funds 2026 04 01'!$A:$A) -> Praxis Growth Index I | C12: =_xlfn.XLOOKUP(D12,[2]Sheet1!$D:$D,[2]Sheet1!$B:$B) -> Equity | D12: =_xlfn.XLOOKUP(A12,'[1]_Funds 2026 04 01'!$B:$B,'[1]_Funds 2026 04 01'!$D:$D) -> Large Cap Growth | E12: =IFERROR(IF(_xlfn.XLOOKUP(A12,july_cfd_bfv_1co!C:C,july_cfd_bfv_1co!G:G)=0,"-",_xlfn.XLOOKUP(A12,july_cfd_bfv_1co!C:C,july_cfd_bfv_1co!G:G)),"-") -> 0.05 | F12: - | G12: =IFERROR(IF(_xlfn.XLOOKUP(A12,july_cfd_bfv_3mo!C:C,july_cfd_bfv_3mo!G:G)=0,"-",_xlfn.XLOOKUP(A12,july_cfd_bfv_3mo!C:C,july_cfd_bfv_3mo!G:G)),"-") -> 0.12 | H12: =IFERROR(IF(_xlfn.XLOOKUP(A12,july_cfd_bfv_4ma!C:C,july_cfd_bfv_4ma!G:G)=0,"-",_xlfn.XLOOKUP(A12,july_cfd_bfv_4ma!C:C,july_cfd_bfv_4ma!G:G)),"-") -> 0.15 | I12: =IFERROR(IF(_xlfn.XLOOKUP(A12,july_cfd_bfv_5ag!C:C,july_cfd_bfv_5ag!G:G)=0,"-",_xlfn.XLOOKUP(A12,july_cfd_bfv_5ag!C:C,july_cfd_bfv_5ag!G:G)),"-") -> 0.2 | J12: =_xlfn.XLOOKUP($A12,'[3]All Funds'!$B:$B,'[3]All Funds'!T:T) -> 0.12031657 | K12: =_xlfn.XLOOKUP($A12,'[3]All Funds'!$B:$B,'[3]All Funds'!U:U) -> 0.10059213 | L12: =_xlfn.XLOOKUP($A12,'[3]All Funds'!$B:$B,'[3]All Funds'!V:V) -> 0.13391571 | M12: =_xlfn.XLOOKUP($A12,'[3]All Funds'!$B:$B,'[3]All Funds'!W:W) -> 0.13041292 | N12: =_xlfn.XLOOKUP($A12,'[3]All Funds'!$B:$B,'[3]All Funds'!X:X) -> 0.20684824 | O12: =_xlfn.XLOOKUP($A12,'[3]All Funds'!$B:$B,'[3]All Funds'!Y:Y) -> 0.12732374
A13: KCVSX | B13: =_xlfn.XLOOKUP(A13,'[1]_Funds 2026 04 01'!$B:$B,'[1]_Funds 2026 04 01'!$A:$A) -> Knights of Columbus Large Cap Value S | C13: =_xlfn.XLOOKUP(D13,[2]Sheet1!$D:$D,[2]Sheet1!$B:$B) -> Equity | D13: =_xlfn.XLOOKUP(A13,'[1]_Funds 2026 04 01'!$B:$B,'[1]_Funds 2026 04 01'!$D:$D) -> Large Cap Value | E13: =IFERROR(IF(_xlfn.XLOOKUP(A13,july_cfd_bfv_1co!C:C,july_cfd_bfv_1co!G:G)=0,"-",_xlfn.XLOOKUP(A13,july_cfd_bfv_1co!C:C,july_cfd_bfv_1co!G:G)),"-") -> 0.05 | F13: - | G13: =IFERROR(IF(_xlfn.XLOOKUP(A13,july_cfd_bfv_3mo!C:C,july_cfd_bfv_3mo!G:G)=0,"-",_xlfn.XLOOKUP(A13,july_cfd_bfv_3mo!C:C,july_cfd_bfv_3mo!G:G)),"-") -> 0.07 | H13: =IFERROR(IF(_xlfn.XLOOKUP(A13,july_cfd_bfv_4ma!C:C,july_cfd_bfv_4ma!G:G)=0,"-",_xlfn.XLOOKUP(A13,july_cfd_bfv_4ma!C:C,july_cfd_bfv_4ma!G:G)),"-") -> 0.05 | I13: =IFERROR(IF(_xlfn.XLOOKUP(A13,july_cfd_bfv_5ag!C:C,july_cfd_bfv_5ag!G:G)=0,"-",_xlfn.XLOOKUP(A13,july_cfd_bfv_5ag!C:C,july_cfd_bfv_5ag!G:G)),"-") -> - | J13: =_xlfn.XLOOKUP($A13,'[3]All Funds'!$B:$B,'[3]All Funds'!T:T) -> 0.048311994 | K13: =_xlfn.XLOOKUP($A13,'[3]All Funds'!$B:$B,'[3]All Funds'!U:U) -> 0.096802634 | L13: =_xlfn.XLOOKUP($A13,'[3]All Funds'!$B:$B,'[3]All Funds'!V:V) -> 0.13651805 | M13: =_xlfn.XLOOKUP($A13,'[3]All Funds'!$B:$B,'[3]All Funds'!W:W) -> 0.11565873 | N13: =_xlfn.XLOOKUP($A13,'[3]All Funds'!$B:$B,'[3]All Funds'!X:X) -> 0.11449155 | O13: =_xlfn.XLOOKUP($A13,'[3]All Funds'!$B:$B,'[3]All Funds'!Y:Y) -> 0.029891785
... A16: GFSZX | B16: =_xlfn.XLOOKUP(A16,'[1]_Funds 2026 04 01'!$B:$B,'[1]_Funds 2026 04 01'!$A:$A) -> GuideStone Funds Strategic Alts Investor | C16: =_xlfn.XLOOKUP(D16,[2]Sheet1!$D:$D,[2]Sheet1!$B:$B) -> Alternatives | D16: =_xlfn.XLOOKUP(A16,'[1]_Funds 2026 04 01'!$B:$B,'[1]_Funds 2026 04 01'!$D:$D) -> Multistrategy | E16: =IFERROR(IF(_xlfn.XLOOKUP(A16,july_cfd_bfv_1co!C:C,july_cfd_bfv_1co!G:G)=0,"-",_xlfn.XLOOKUP(A16,july_cfd_bfv_1co!C:C,july_cfd_bfv_1co!G:G)),"-") -> 0.05 | F16: - | G16: =IFERROR(IF(_xlfn.XLOOKUP(A16,july_cfd_bfv_3mo!C:C,july_cfd_bfv_3mo!G:G)=0,"-",_xlfn.XLOOKUP(A16,july_cfd_bfv_3mo!C:C,july_cfd_bfv_3mo!G:G)),"-") -> 0.04 | H16: =IFERROR(IF(_xlfn.XLOOKUP(A16,july_cfd_bfv_4ma!C:C,july_cfd_bfv_4ma!G:G)=0,"-",_xlfn.XLOOKUP(A16,july_cfd_bfv_4ma!C:C,july_cfd_bfv_4ma!G:G)),"-") -> - | I16: =IFERROR(IF(_xlfn.XLOOKUP(A16,july_cfd_bfv_5ag!C:C,july_cfd_bfv_5ag!G:G)=0,"-",_xlfn.XLOOKUP(A16,july_cfd_bfv_5ag!C:C,july_cfd_bfv_5ag!G:G)),"-") -> - | J16: =_xlfn.XLOOKUP($A16,'[3]All Funds'!$B:$B,'[3]All Funds'!T:T) -> 0.73609597 | K16: =_xlfn.XLOOKUP($A16,'[3]All Funds'!$B:$B,'[3]All Funds'!U:U) -> 0.63838765 | L16: =_xlfn.XLOOKUP($A16,'[3]All Funds'!$B:$B,'[3]All Funds'!V:V) -> 0.54991616 | M16: =_xlfn.XLOOKUP($A16,'[3]All Funds'!$B:$B,'[3]All Funds'!W:W) -> 0.49269777 | N16: =_xlfn.XLOOKUP($A16,'[3]All Funds'!$B:$B,'[3]All Funds'!X:X) -> 0.43174297 | O16: =_xlfn.XLOOKUP($A16,'[3]All Funds'!$B:$B,'[3]All Funds'!Y:Y) -> 0.78050048
E17: =SUM(E1:E16) -> 1 | F17: =SUM(F1:F16) -> 0 | G17: =SUM(G1:G16) -> 1 | H17: =SUM(H1:H16) -> 1 | I17: =SUM(I1:I16) -> 1

Sheet july_cfd_bfv_1co
A1: Investment | B1: Fees/Trading Rules | C1: Fund ID | D1: Balance | E1: Units | F1: Price | G1: Allocation Percent
A2: Ave Maria Bond R | B2: Trade Rules | C2: AVEFX | D2: 147.21 | E2: 12.176 | F2: 12.09 | G2: 0.12
A3: GuideStone International Equity Inv | B3: Trade Rules | C3: GIEZX | D3: 62.75 | E3: 3.64 | F3: 17.24 | G3: 0.05
A4: Guidestone Global Bond Fund Inv | B4: Trade Rules | C4: GGBFX | D4: 84.03 | E4: 10.027 | F4: 8.38 | G4: 0.07
A5: Timothy Plan High Yield Bond I | B5: Trade Rules | C5: TPHIX | D5: 62.36 | E5: 6.96 | F5: 8.96 | G5: 0.05
A6: Timothy Plan Fixed Income I | B6: Trade Rules | C6: TPFIX | D6: 192.54 | E6: 21.979 | F6: 8.76 | G6: 0.16
A7: American Funds US Government Sec R6 | B7: Trade Rules | C7: RGVGX | D7: 178.16 | E7: 15.711 | F7: 11.34 | G7: 0.15
A8: GuideStone Equity Index Inv | B8: Trade Rules | C8: GEQZX | D8: 64.28 | E8: 0.848 | F8: 75.8 | G8: 0.05
A9: Praxis Growth Index I | B9: Trade Rules | C9: MMDEX | D9: 65.42 | E9: 1.043 | F9: 62.72 | G9: 0.05
A10: Knights of Columbus Large Cap Value S | B10: Trade Rules | C10: KCVSX | D10: 61.54 | E10: 2.957 | F10: 20.81 | G10: 0.05
A11: Eventide Balanced Fund Class I | B11: Trade Rules | C11: ETIMX | D11: 116.95 | E11: 7.902 | F11: 14.8 | G11: 0.1
A12: GuideStone Funds Strategic Alts Investor | B12: Trade Rules | C12: GFSZX | D12: 62.77 | E12: 6.845 | F12: 9.17 | G12: 0.05
A13: Knights of Columbus Limited Duration S | B13: Trade Rules | C13: KCLSX | D13: 124.33 | E13: 12.911 | F13: 9.63 | G13: 0.1

Sheet Sheet9

Sheet july_cfd_bfv_3mo
A1: Investment | B1: Fees/Trading Rules | C1: Fund ID | D1: Balance | E1: Units | F1: Price | G1: Allocation Percent
A2: Ave Maria Bond R | B2: Trade Rules | C2: AVEFX | D2: 7824.29 | E2: 647.171 | F2: 12.09 | G2: 0.07
A3: GuideStone Funds Emerging Mkts Eq Inv | B3: Trade Rules | C3: GEMZX | D3: 4591.63 | E3: 294.903 | F3: 15.57 | G3: 0.04
A4: GuideStone International Equity Inv | B4: Trade Rules | C4: GIEZX | D4: 14837.3 | E4: 860.633 | F4: 17.24 | G4: 0.13
A5: Guidestone Global Bond Fund Inv | B5: Trade Rules | C5: GGBFX | D5: 5507.8 | E5: 657.257 | F5: 8.38 | G5: 0.05
A6: Timothy Plan High Yield Bond I | B6: Trade Rules | C6: TPHIX | D6: 5649.55 | E6: 630.53 | F6: 8.96 | G6: 0.05
A7: Timothy Plan Fixed Income I | B7: Trade Rules | C7: TPFIX | D7: 13227.27 | E7: 1509.962 | F7: 8.76 | G7: 0.12
A8: American Funds US Government Sec R6 | B8: Trade Rules | C8: RGVGX | D8: 5455.76 | E8: 481.107 | F8: 11.34 | G8: 0.05
A9: GuideStone Equity Index Inv | B9: Trade Rules | C9: GEQZX | D9: 6998.08 | E9: 92.323 | F9: 75.8 | G9: 0.06
A10: Praxis Growth Index I | B10: Trade Rules | C10: MMDEX | D10: 14220.27 | E10: 226.726 | F10: 62.72 | G10: 0.12
A11: Knights of Columbus Large Cap Value S | B11: Trade Rules | C11: KCVSX | D11: 7815.88 | E11: 375.583 | F11: 20.81 | G11: 0.07
A12: Timothy Plan Small/Mid Cap Growth Cl A | B12: Trade Rules | C12: TAAGX | D12: 10815.45 | E12: 612.08 | F12: 17.67 | G12: 0.1
A13: Eventide Balanced Fund Class I | B13: Trade Rules | C13: ETIMX | D13: 5382.19 | E13: 363.661 | F13: 14.8 | G13: 0.05
... A15: Timothy Plan Small Cap Value I | B15: Trade Rules | C15: TPVIX | D15: 5195.6 | E15: 262.67 | F15: 19.78 | G15: 0.05

Sheet july_cfd_bfv_4ma
A1: Investment | B1: Fees/Trading Rules | C1: Fund ID | D1: Balance | E1: Units | F1: Price | G1: Allocation Percent
A2: Ave Maria Bond R | B2: Trade Rules | C2: AVEFX | D2: 11608.78 | E2: 960.196 | F2: 12.09 | G2: 0.07
A3: GuideStone Funds Emerging Mkts Eq Inv | B3: Trade Rules | C3: GEMZX | D3: 11806.49 | E3: 758.286 | F3: 15.57 | G3: 0.07
A4: GuideStone International Equity Inv | B4: Trade Rules | C4: GIEZX | D4: 30502.45 | E4: 1769.284 | F4: 17.24 | G4: 0.18
A5: Guidestone Global Bond Fund Inv | B5: Trade Rules | C5: GGBFX | D5: 8143.94 | E5: 971.83 | F5: 8.38 | G5: 0.05
A6: Timothy Plan Fixed Income I | B6: Trade Rules | C6: TPFIX | D6: 11419.99 | E6: 1303.651 | F6: 8.76 | G6: 0.07
A7: GuideStone Equity Index Inv | B7: Trade Rules | C7: GEQZX | D7: 20785.74 | E7: 274.218 | F7: 75.8 | G7: 0.12
A8: Praxis Growth Index I | B8: Trade Rules | C8: MMDEX | D8: 26424.09 | E8: 421.302 | F8: 62.72 | G8: 0.15
A9: Knights of Columbus Large Cap Value S | B9: Trade Rules | C9: KCVSX | D9: 8296.39 | E9: 398.673 | F9: 20.81 | G9: 0.05
A10: Timothy Plan Small/Mid Cap Growth Cl A | B10: Trade Rules | C10: TAAGX | D10: 22091.41 | E10: 1250.222 | F10: 17.67 | G10: 0.14
A11: Timothy Plan Small Cap Value I | B11: Trade Rules | C11: TPVIX | D11: 15367.87 | E11: 776.939 | F11: 19.78 | G11: 0.1

Sheet july_cfd_bfv_5ag
A1: Investment | B1: Fees/Trading Rules | C1: Fund ID | D1: Balance | E1: Units | F1: Price | G1: Allocation Percent
A2: GuideStone Funds Emerging Mkts Eq Inv | B2: Trade Rules | C2: GEMZX | D2: 273936.96 | E2: 17593.897 | F2: 15.57 | G2: 0.11
A3: GuideStone International Equity Inv | B3: Trade Rules | C3: GIEZX | D3: 480806.86 | E3: 27889.029 | F3: 17.24 | G3: 0.19
A4: GuideStone Equity Index Inv | B4: Trade Rules | C4: GEQZX | D4: 465581.31 | E4: 6142.234 | F4: 75.8 | G4: 0.18
A5: Praxis Growth Index I | B5: Trade Rules | C5: MMDEX | D5: 526637.77 | E5: 8396.648 | F5: 62.72 | G5: 0.2
A6: Timothy Plan Small/Mid Cap Growth Cl A | B6: Trade Rules | C6: TAAGX | D6: 393092.06 | E6: 22246.296 | F6: 17.67 | G6: 0.17
A7: Timothy Plan Small Cap Value I | B7: Trade Rules | C7: TPVIX | D7: 342773.8 | E7: 17329.312 | F7: 19.78 | G7: 0.15

Sheet Sheet13
